kem_my_regression/__init__.py
kem_my_regression/regression.py
kem_my_regression-1.0.0.dist-info/licenses/LICENSE.txt
kem_my_regression-1.0.0.dist-info/METADATA
kem_my_regression-1.0.0.dist-info/WHEEL
kem_my_regression-1.0.0.dist-info/top_level.txt
kem_my_regression-1.0.0.dist-info/RECORD
