Metadata-Version: 2.4
Name: kem_my_regression
Version: 1.0.0
Summary: A simple linear regression package implemented from scratch.
Home-page: https://pypi.org/project/my_regression/
Author: Kambouz Nouha
Author-email: kambouz907@gmail.com
License: MIT
License-File: LICENSE.txt
Requires-Dist: numpy
Dynamic: author
Dynamic: author-email
Dynamic: description
Dynamic: description-content-type
Dynamic: home-page
Dynamic: license
Dynamic: license-file
Dynamic: requires-dist
Dynamic: summary
